LICENSE.txt
MANIFEST.in
README.md
setup.py
clog/__init__.py
clog/clog.py
clog.egg-info/PKG-INFO
clog.egg-info/SOURCES.txt
clog.egg-info/dependency_links.txt
clog.egg-info/requires.txt
clog.egg-info/top_level.txt