Metadata-Version: 2.1
Name: clog
Version: 0.3.0
Summary: pretty-print with color
Home-page: https://github.com/bradmontgomery/clog
Author: Brad Montgomery
Author-email: brad@bradmontgomery.net
License: MIT
Project-URL: Bug Tracker, https://github.com/bradmontgomery/clog/issues
Platform: UNKNOWN
Classifier: Development Status :: 4 - Beta
Classifier: Programming Language :: Python
Classifier: Intended Audience :: Developers
Classifier: Operating System :: OS Independent
Classifier: Programming Language :: Python
Classifier: Programming Language :: Python :: 3
Classifier: Topic :: Software Development :: Libraries :: Python Modules
Requires-Python: >=3.6
